{
    "ports": [
        {
            "name": "VM1-TE1",
            "location": "localhost:5551"
        },
        {
            "name": "VM2-TE1",
            "location": "192.168.0.61:5551"
        }
    ],
    "layer1": [
        {
            "name": "l1",
            "port_names": [
                "VM1-TE1",
                "VM2-TE1"
            ],
            "speed": "speed_100_gbps"
        }
    ],
    "flows": [
        {
            "name": "f1 VM1-TE1 -> VM2-TE1",
            "tx_rx": {
                "choice": "port",
                "port": {
                    "tx_name": "VM1-TE1",
                    "rx_name": "VM2-TE1"
                }
            },
            "metrics": {
                "enable": true
            },
            "size": {
                "choice": "fixed",
                "fixed": 9000
            },
            "rate": {
                "choice": "percentage",
                "percentage": 100 
            },
            "duration": {
                "choice": "fixed_seconds",
                "fixed_seconds": {
                    "seconds": 60
                }
            },
            "packet": [
                {
                    "choice": "ethernet",
                    "ethernet": {
                        "dst": {
                            "choice": "value",
                            "value": "00:15:5d:a4:08:3e"
                        },
                        "src": {
                            "choice": "value",
                            "value": "00:15:5d:a4:08:25"
                        }
                    }
                },
                {
                    "choice": "ipv4",
                    "ipv4": {
                        "dst": {
                            "choice": "value",
                            "value": "1.1.1.1"
                        },
                        "src": {
                            "choice": "value",
                            "value": "1.1.1.2"
                        }
                    }
                }
            ]
        }
    ]
}
